hichub/Constants.py
hichub/__init__.py
hichub/associate.py
hichub/call_diff.py
hichub/callhub.py
hichub/convert_multi_hic_to_txt.py
hichub/find_gene.py
hichub/plot.py
hichub/test.py
hichub-1.2.0.data/scripts/hichub
hichub-1.2.0.dist-info/LICENSE
hichub-1.2.0.dist-info/METADATA
hichub-1.2.0.dist-info/WHEEL
hichub-1.2.0.dist-info/top_level.txt
hichub-1.2.0.dist-info/RECORD
