Metadata-Version: 2.1
Name: hichub
Version: 1.2.0
Summary: Comprehensive Network Analysis for HiC
Home-page: https://github.com/WeiqunPengLab/HiCHub
Author: Xiang Li, Shuang Yuan, Shaoqi Zhu
Author-email: gwpenglab@gmail.com
Project-URL: Bug Reports, https://github.com/WeiqunPengLab/HiCHub
Project-URL: Funding, https://github.com/WeiqunPengLab/HiCHub
Project-URL: Say Thanks!, https://github.com/WeiqunPengLab/HiCHub
Project-URL: Source, https://github.com/WeiqunPengLab/HiCHub
Keywords: HiC,graph,Hub
Classifier: Development Status :: 3 - Alpha
Classifier: Intended Audience :: Science/Research
Classifier: Topic :: Software Development :: Build Tools
Classifier: License :: OSI Approved :: MIT License
Classifier: Programming Language :: Python :: 3
Classifier: Programming Language :: Python :: 3.3
Classifier: Programming Language :: Python :: 3.6
Classifier: Programming Language :: Python :: 3.7
Classifier: Programming Language :: Python :: 3.8
Classifier: Programming Language :: Python :: 3.9
Requires-Python: >=3.0, <4
License-File: LICENSE
Requires-Dist: pandas
Requires-Dist: numpy
Requires-Dist: pybedtools
Requires-Dist: scipy
Requires-Dist: python-igraph
